[{"id":97019,"fullName":"Ivo VAJGL","nationalPoliticalGroup":"DeSUS - Demokratična Stranka Upokojencev Slovenije","country":"Slovenia","actavote":"good","gdprvote":"good","a13vote":"bad","biovote":"bad","terrorvote":"bad","overall":"bad"},
{"id":125003,"fullName":"Igor ŠOLTES","nationalPoliticalGroup":"Lista dr. Igorja Šoltesa","country":"Slovenia","actavote":"none","gdprvote":"none","a13vote":"good","biovote":"good","terrorvote":"bad","overall":"neutral"},
{"id":23693,"fullName":"Alojz PETERLE","nationalPoliticalGroup":"Nova Slovenija – Krščanski demokrati","country":"Slovenia","actavote":"good","gdprvote":"none","a13vote":"bad","biovote":"bad","terrorvote":"good","overall":"neutral"},
{"id":96933,"fullName":"Milan ZVER","nationalPoliticalGroup":"Slovenska demokratska stranka","country":"Slovenia","actavote":"good","gdprvote":"good","a13vote":"good","biovote":"none","terrorvote":"neutral","overall":"good"},
{"id":125103,"fullName":"Patricija ŠULIN","nationalPoliticalGroup":"Slovenska demokratska stranka","country":"Slovenia","actavote":"none","gdprvote":"none","a13vote":"good","biovote":"bad","terrorvote":"good","overall":"neutral"},
{"id":125104,"fullName":"Romana TOMC","nationalPoliticalGroup":"Slovenska demokratska stranka","country":"Slovenia","actavote":"none","gdprvote":"none","a13vote":"good","biovote":"bad","terrorvote":"good","overall":"neutral"},
{"id":125004,"fullName":"Franc BOGOVIČ","nationalPoliticalGroup":"Slovenska ljudska stranka","country":"Slovenia","actavote":"none","gdprvote":"none","a13vote":"bad","biovote":"bad","terrorvote":"good","overall":"neutral"},
{"id":96911,"fullName":"Tanja FAJON","nationalPoliticalGroup":"Socialni demokrati","country":"Slovenia","actavote":"good","gdprvote":"good","a13vote":"good","biovote":"none","terrorvote":"bad","overall":"neutral"}]