[{"id":102887,"fullName":"Béla KOVÁCS","nationalPoliticalGroup":"-","country":"Hungary","actavote":"good","gdprvote":"good","a13vote":"none","biovote":"bad","terrorvote":"bad","overall":"neutral"},
{"id":96661,"fullName":"Krisztina MORVAI","nationalPoliticalGroup":"-","country":"Hungary","actavote":"good","gdprvote":"good","a13vote":"none","biovote":"neutral","terrorvote":"bad","overall":"neutral"},
{"id":124722,"fullName":"Csaba MOLNÁR","nationalPoliticalGroup":"Demokratikus Koalíció","country":"Hungary","actavote":"none","gdprvote":"none","a13vote":"bad","biovote":"bad","terrorvote":"bad","overall":"bad"},
{"id":124723,"fullName":"Péter NIEDERMÜLLER","nationalPoliticalGroup":"Demokratikus Koalíció","country":"Hungary","actavote":"none","gdprvote":"none","a13vote":"good","biovote":"bad","terrorvote":"none","overall":"neutral"},
{"id":124721,"fullName":"Benedek JÁVOR","nationalPoliticalGroup":"Együtt 2014 - Párbeszéd Magyarországért","country":"Hungary","actavote":"none","gdprvote":"none","a13vote":"none","biovote":"good","terrorvote":"bad","overall":"neutral"},
{"id":96829,"fullName":"Ádám KÓSA","nationalPoliticalGroup":"Fidesz-Magyar Polgári Szövetség-Kereszténydemokrata Néppárt","country":"Hungary","actavote":"good","gdprvote":"good","a13vote":"bad","biovote":"bad","terrorvote":"neutral","overall":"neutral"},
{"id":124714,"fullName":"Andor DELI","nationalPoliticalGroup":"Fidesz-Magyar Polgári Szövetség-Kereszténydemokrata Néppárt","country":"Hungary","actavote":"none","gdprvote":"none","a13vote":"bad","biovote":"none","terrorvote":"neutral","overall":"neutral"},
{"id":23816,"fullName":"András GYÜRK","nationalPoliticalGroup":"Fidesz-Magyar Polgári Szövetség-Kereszténydemokrata Néppárt","country":"Hungary","actavote":"good","gdprvote":"good","a13vote":"none","biovote":"bad","terrorvote":"none","overall":"neutral"},
{"id":124712,"fullName":"Andrea BOCSKOR","nationalPoliticalGroup":"Fidesz-Magyar Polgári Szövetség-Kereszténydemokrata Néppárt","country":"Hungary","actavote":"none","gdprvote":"none","a13vote":"bad","biovote":"bad","terrorvote":"neutral","overall":"bad"},
{"id":28135,"fullName":"György SCHÖPFLIN","nationalPoliticalGroup":"Fidesz-Magyar Polgári Szövetség-Kereszténydemokrata Néppárt","country":"Hungary","actavote":"good","gdprvote":"good","a13vote":"none","biovote":"none","terrorvote":"none","overall":"neutral"},
{"id":23821,"fullName":"József SZÁJER","nationalPoliticalGroup":"Fidesz-Magyar Polgári Szövetség-Kereszténydemokrata Néppárt","country":"Hungary","actavote":"good","gdprvote":"good","a13vote":"bad","biovote":"bad","terrorvote":"good","overall":"neutral"},
{"id":28150,"fullName":"Kinga GÁL","nationalPoliticalGroup":"Fidesz-Magyar Polgári Szövetség-Kereszténydemokrata Néppárt","country":"Hungary","actavote":"none","gdprvote":"good","a13vote":"bad","biovote":"bad","terrorvote":"neutral","overall":"bad"},
{"id":39726,"fullName":"László TŐKÉS","nationalPoliticalGroup":"Fidesz-Magyar Polgári Szövetség-Kereszténydemokrata Néppárt","country":"Hungary","actavote":"none","gdprvote":"none","a13vote":"bad","biovote":"bad","terrorvote":"none","overall":"bad"},
{"id":28141,"fullName":"Lívia JÁRÓKA","nationalPoliticalGroup":"Fidesz-Magyar Polgári Szövetség-Kereszténydemokrata Néppárt","country":"Hungary","actavote":"good","gdprvote":"good","a13vote":"none","biovote":"bad","terrorvote":"neutral","overall":"neutral"},
{"id":124711,"fullName":"Norbert ERDŐS","nationalPoliticalGroup":"Fidesz-Magyar Polgári Szövetség-Kereszténydemokrata Néppárt","country":"Hungary","actavote":"none","gdprvote":"none","a13vote":"bad","biovote":"bad","terrorvote":"neutral","overall":"bad"},
{"id":96826,"fullName":"Tamás DEUTSCH","nationalPoliticalGroup":"Fidesz-Magyar Polgári Szövetség-Kereszténydemokrata Néppárt","country":"Hungary","actavote":"good","gdprvote":"none","a13vote":"bad","biovote":"bad","terrorvote":"neutral","overall":"bad"},
{"id":96877,"fullName":"Zoltán BALCZÓ","nationalPoliticalGroup":"Jobbik Magyarországért Mozgalom","country":"Hungary","actavote":"none","gdprvote":"none","a13vote":"good","biovote":"bad","terrorvote":"bad","overall":"neutral"},
{"id":124715,"fullName":"György HÖLVÉNYI","nationalPoliticalGroup":"Kereszténydemokrata Néppárt","country":"Hungary","actavote":"none","gdprvote":"none","a13vote":"bad","biovote":"bad","terrorvote":"neutral","overall":"bad"},
{"id":124720,"fullName":"Tamás MESZERICS","nationalPoliticalGroup":"Lehet Más A Politika","country":"Hungary","actavote":"none","gdprvote":"none","a13vote":"good","biovote":"none","terrorvote":"none","overall":"neutral"},
{"id":124705,"fullName":"István UJHELYI","nationalPoliticalGroup":"Magyar Szocialista Párt","country":"Hungary","actavote":"none","gdprvote":"none","a13vote":"none","biovote":"none","terrorvote":"none","overall":"none"},
{"id":124703,"fullName":"Tibor SZANYI","nationalPoliticalGroup":"Magyar Szocialista Párt","country":"Hungary","actavote":"none","gdprvote":"none","a13vote":"good","biovote":"bad","terrorvote":"bad","overall":"neutral"}]